orbis_plugin_storage_csv_result_list/__init__.py
orbis_plugin_storage_csv_result_list/main.py
orbis_plugin_storage_csv_result_list-2.2.4.dist-info/LICENSE
orbis_plugin_storage_csv_result_list-2.2.4.dist-info/METADATA
orbis_plugin_storage_csv_result_list-2.2.4.dist-info/WHEEL
orbis_plugin_storage_csv_result_list-2.2.4.dist-info/top_level.txt
orbis_plugin_storage_csv_result_list-2.2.4.dist-info/RECORD
